PlasmaCalcs/__init__.py
PlasmaCalcs/defaults.py
PlasmaCalcs/errors.py
PlasmaCalcs/plasma_calculator.py
PlasmaCalcs/addons/__init__.py
PlasmaCalcs/addons/addon_tools.py
PlasmaCalcs/addons/instability_tools/__init__.py
PlasmaCalcs/addons/instability_tools/instability_data_tools.py
PlasmaCalcs/addons/instability_tools/instability_quantity_loader.py
PlasmaCalcs/addons/instability_tools/instability_theory_tools.py
PlasmaCalcs/addons/instability_tools/instability_xarray_accessor.py
PlasmaCalcs/addons/tfbi/__init__.py
PlasmaCalcs/addons/tfbi/tfbi_imports.py
PlasmaCalcs/addons/tfbi/tfbi_loader.py
PlasmaCalcs/addons/tfbi/tfbi_misc.py
PlasmaCalcs/addons/tfbi/tfbi_solver.py
PlasmaCalcs/dimensions/__init__.py
PlasmaCalcs/dimensions/behavior.py
PlasmaCalcs/dimensions/components.py
PlasmaCalcs/dimensions/fluids.py
PlasmaCalcs/dimensions/main_dimensions.py
PlasmaCalcs/dimensions/maindims_chunking.py
PlasmaCalcs/dimensions/snaps.py
PlasmaCalcs/dimensions/subsampling.py
PlasmaCalcs/dimensions/dimension_tools/__init__.py
PlasmaCalcs/dimensions/dimension_tools/dim_point.py
PlasmaCalcs/dimensions/dimension_tools/dimension.py
PlasmaCalcs/dimensions/dimension_tools/dimension_haver.py
PlasmaCalcs/dimensions/dimension_tools/dimension_value.py
PlasmaCalcs/dimensions/dimension_tools/multi_slices.py
PlasmaCalcs/hookups/__init__.py
PlasmaCalcs/hookups/bifrost/__init__.py
PlasmaCalcs/hookups/bifrost/bifrost_bases.py
PlasmaCalcs/hookups/bifrost/bifrost_calculator.py
PlasmaCalcs/hookups/bifrost/bifrost_direct_loader.py
PlasmaCalcs/hookups/bifrost/bifrost_efield.py
PlasmaCalcs/hookups/bifrost/bifrost_eos_loader.py
PlasmaCalcs/hookups/bifrost/bifrost_io_tools.py
PlasmaCalcs/hookups/bifrost/bifrost_snaps.py
PlasmaCalcs/hookups/bifrost/bifrost_stagger.py
PlasmaCalcs/hookups/bifrost/bifrost_units.py
PlasmaCalcs/hookups/bifrost/bifrost_multifluid/__init__.py
PlasmaCalcs/hookups/bifrost/bifrost_multifluid/bifrost_multifluid_calculator.py
plasmacalcs-2025.11.0.dist-info/LICENSE
plasmacalcs-2025.11.0.dist-info/WHEEL
plasmacalcs-2025.11.0.dist-info/METADATA
plasmacalcs-2025.11.0.dist-info/RECORD
