Metadata-Version: 2.1
Name: PlasmaCalcs
Version: 2025.11.0
Summary: Consistent interface for plasma calculations from any inputs.
Author-email: Sam Evans <sevans7@bu.edu>
Requires-Python: >=3.9
Requires-Dist: xarray >= 2024.7.0
Requires-Dist: numpy
Requires-Dist: matplotlib
Requires-Dist: IPython
Requires-Dist: colorcet ; extra == "all"
Requires-Dist: h5netcdf ; extra == "all"
Requires-Dist: h5py ; extra == "all"
Requires-Dist: openpmd-api ; extra == "all"
Requires-Dist: pytest ; extra == "all"
Requires-Dist: scipy ; extra == "all"
Requires-Dist: tfbi_theory ; extra == "all"
Requires-Dist: colorcet ; extra == "all_fast"
Requires-Dist: h5netcdf ; extra == "all_fast"
Requires-Dist: h5py ; extra == "all_fast"
Requires-Dist: pytest ; extra == "all_fast"
Requires-Dist: scipy ; extra == "all_fast"
Requires-Dist: tfbi_theory ; extra == "all_fast"
Requires-Dist: scipy ; extra == "bifrost"
Requires-Dist: h5py ; extra == "eppic"
Requires-Dist: openpmd ; extra == "eppic"
Requires-Dist: colorcet ; extra == "most"
Requires-Dist: h5netcdf ; extra == "most"
Requires-Dist: h5py ; extra == "most"
Requires-Dist: pytest ; extra == "most"
Requires-Dist: scipy ; extra == "most"
Requires-Dist: colorcet ; extra == "plots"
Requires-Dist: h5netcdf ; extra == "tests"
Requires-Dist: h5py ; extra == "tests"
Requires-Dist: pytest ; extra == "tests"
Requires-Dist: scipy ; extra == "tests"
Requires-Dist: tfbi_theory ; extra == "tests"
Requires-Dist: tfbi_theory ; extra == "tfbi"
Requires-Dist: h5netcdf ; extra == "xarray_io"
Requires-Dist: scipy ; extra == "xarray_io"
Project-URL: source-code, https://gitlab.com/Sevans7/plasmacalcs
Provides-Extra: all
Provides-Extra: all_fast
Provides-Extra: bifrost
Provides-Extra: eppic
Provides-Extra: most
Provides-Extra: plots
Provides-Extra: tests
Provides-Extra: tfbi
Provides-Extra: xarray_io
